{".class": "MypyFile", "_fullname": "Helper", "is_partial_stub_package": false, "is_stub": false, "names": {".class": "SymbolTable", "__doc__": {".class": "SymbolTableNode", "kind": "Gdef", "node": {".class": "Var", "flags": ["is_ready"], "fullname": "Helper.__doc__", "name": "__doc__", "type": "builtins.str"}}, "__file__": {".class": "SymbolTableNode", "kind": "Gdef", "node": {".class": "Var", "flags": ["is_ready"], "fullname": "Helper.__file__", "name": "__file__", "type": "builtins.str"}}, "__name__": {".class": "SymbolTableNode", "kind": "Gdef", "node": {".class": "Var", "flags": ["is_ready"], "fullname": "Helper.__name__", "name": "__name__", "type": "builtins.str"}}, "__package__": {".class": "SymbolTableNode", "kind": "Gdef", "node": {".class": "Var", "flags": ["is_ready"], "fullname": "Helper.__package__", "name": "__package__", "type": "builtins.str"}}, "add_two_values": {".class": "SymbolTableNode", "kind": "Gdef", "node": {".class": "FuncDef", "arg_kinds": [0, 0], "arg_names": ["a", "b"], "flags": [], "fullname": "Helper.add_two_values", "name": "add_two_values", "type": null}}, "convert_to_date": {".class": "SymbolTableNode", "kind": "Gdef", "node": {".class": "FuncDef", "arg_kinds": [0], "arg_names": ["timestamp"], "flags": [], "fullname": "Helper.convert_to_date", "name": "convert_to_date", "type": null}}, "datetime": {".class": "SymbolTableNode", "cross_ref": "datetime", "kind": "Gdef"}, "format_date": {".class": "SymbolTableNode", "kind": "Gdef", "node": {".class": "FuncDef", "arg_kinds": [0], "arg_names": ["date"], "flags": [], "fullname": "Helper.format_date", "name": "format_date", "type": null}}, "format_timestamp": {".class": "SymbolTableNode", "kind": "Gdef", "node": {".class": "FuncDef", "arg_kinds": [0], "arg_names": ["time"], "flags": [], "fullname": "Helper.format_timestamp", "name": "format_timestamp", "type": null}}}, "path": ".\\Helper.py"}